MANIFEST.in
README.md
setup.py
ananas_doc.egg-info/PKG-INFO
ananas_doc.egg-info/SOURCES.txt
ananas_doc.egg-info/dependency_links.txt
ananas_doc.egg-info/entry_points.txt
ananas_doc.egg-info/not-zip-safe
ananas_doc.egg-info/requires.txt
ananas_doc.egg-info/top_level.txt
ananasdoc/__init__.py
ananasdoc/conf.py
ananasdoc/datetimeutil.py
ananasdoc/error.py
ananasdoc/exception.py
ananasdoc/index.rst
ananasdoc/log.py
ananasdoc/makefile.py
ananasdoc/rest_api.py
ananasdoc/start.py
ananasdoc/table.py
ananasdoc/template.py
ananasdoc/utils.py
ananasdoc/template/_static/css/badge_only.css
ananasdoc/template/_static/css/newstyle.css
ananasdoc/template/_static/css/theme.css
ananasdoc/template/_static/images/logo.png
ananasdoc/template/_static/js/modernizr.min.js
ananasdoc/template/_static/js/theme.js
ananasdoc/template/_version/.note
ananasdoc/template/_version/.version
ananasdoc/template/_version/version.yml