Metadata-Version: 1.0
Name: ananas-doc
Version: 1.2.3
Summary: docs tools
Home-page: https://github.com/Lonersun/ananas-doc
Author: Lonerusn
Author-email: yang.guo.sun@gmail.com
License: Apache License 2.0
Keywords: docs tools
Platform: any
